MANIFEST.in
README.rst
setup.cfg
setup.py
openspending/__init__.py
openspending/reference/__init__.py
openspending/reference/category.py
openspending/reference/country.py
openspending/reference/currency.py
openspending/reference/language.py
openspending/reference/util.py
openspending/reference/data/countries.csv
openspending/reference/data/currency.json
openspending/reference/data/language.json
openspending/validation/__init__.py
openspending/validation/data.py
openspending/validation/util.py
openspending/validation/model/__init__.py
openspending/validation/model/common.py
openspending/validation/model/dataset.py
openspending/validation/model/mapping.py
openspending/validation/model/migration.py
openspending/validation/model/predicates.py
openspending/validation/model/views.py
openspending/validationcli/__init__.py
openspending/validationcli/udr.py
openspending/validationtest/unit/__init__.py
openspending/validationtest/unit/validation/__init__.py
openspending/validationtest/unit/validation/test_common.py
openspending/validationtest/unit/validation/test_currency.py
openspending/validationtest/unit/validation/test_data.py
openspending/validationtest/unit/validation/test_dataset.py
openspending/validationtest/unit/validation/test_mapping.py
openspending/validationtest/unit/validation/test_migration.py
openspending/validationtest/unit/validation/test_views.py
osvalidate.egg-info/PKG-INFO
osvalidate.egg-info/SOURCES.txt
osvalidate.egg-info/dependency_links.txt
osvalidate.egg-info/entry_points.txt
osvalidate.egg-info/namespace_packages.txt
osvalidate.egg-info/not-zip-safe
osvalidate.egg-info/pbr.json
osvalidate.egg-info/requires.txt
osvalidate.egg-info/top_level.txt