Metadata-Version: 1.0
Name: osvalidate
Version: 2014-12-21.01
Summary: OpenSpending Model/Data Validation
Home-page: http://github.com/okfn/osvalidate
Author: Open Knowledge Foundation
Author-email: openspending-dev at lists okfn org
License: GPLv3
Platform: UNKNOWN
